{
  "items": [
    { "name": "He Got Game (Original)", "img": "placeholder" },
    { "name": "Bred (Original)", "img": "placeholder" },
    { "name": "Playoff (Original)", "img": "placeholder" },
    { "name": "Flint (Original)", "img": "placeholder" },
    { "name": "Black Cat (Original)", "img": "placeholder" },
    { "name": "Altitude (Original)", "img": "placeholder" },
    { "name": "Chutney (Original)", "img": "placeholder" },
    { "name": "Navy (Original)", "img": "placeholder" },
    { "name": "White/Black (Original)", "img": "placeholder" },
    { "name": "Low (Original)", "img": "placeholder" },
    { "name": "Wheat (Original)", "img": "placeholder" },
    { "name": "Black/True Red (Original)", "img": "placeholder" },
    { "name": "Reflective Silver (Original)", "img": "placeholder" },
    { "name": "White/Team Red (Original)", "img": "placeholder" },
    { "name": "Playoff Low (Original)", "img": "placeholder" },
    { "name": "Bred Low (Original)", "img": "placeholder" },
    { "name": "Navy Low (Original)", "img": "placeholder" },
    { "name": "Cement Grey Toe", "img": "placeholder" },
    { "name": "Black/Infrared", "img": "placeholder" },
    { "name": "Playoff Low 2015", "img": "placeholder" },
    { "name": "Hologram", "img": "placeholder" },
    { "name": "Singles Day", "img": "placeholder" },
    { "name": "Gym Red", "img": "placeholder" },
    { "name": "Island Green", "img": "placeholder" },
    { "name": "Lucky Green", "img": "placeholder" },
    { "name": "Reverse He Got Game", "img": "placeholder" },
    { "name": "Flint Grey (2020)", "img": "placeholder" },
    { "name": "Starfish", "img": "placeholder" },
    { "name": "Shattered Backboard", "img": "placeholder" },
    { "name": "Gym Red/Flint", "img": "placeholder" },
    { "name": "Hyper Royal", "img": "placeholder" },
    { "name": "Celtics", "img": "placeholder" }
  ]
}
